tkdial/__init__.py
tkdial/imageknob.py
tkdial/jogwheel.py
tkdial/meter.py
tkdial/scrollknob.py
tkdial/tkdial.py
tkdial-0.0.7.dist-info/LICENSE
tkdial-0.0.7.dist-info/METADATA
tkdial-0.0.7.dist-info/WHEEL
tkdial-0.0.7.dist-info/dependency_links.txt
tkdial-0.0.7.dist-info/top_level.txt
tkdial-0.0.7.dist-info/RECORD
