Metadata-Version: 2.1
Name: tkdial
Version: 0.0.7
Summary: Rotatory dial-knob widgets for Tkinter.
Home-page: https://github.com/Akascape/TkDial
Author: Akash Bora
License: Creative Commons Zero v1.0 Universal
Keywords: tkinter,tkinter-dial,tkinter-widget,tkinter-knob,tkinter-meter,tkinter-dial-knob,dial-knob-widget,tkinter-gui
Classifier: License :: CC0 1.0 Universal (CC0 1.0) Public Domain Dedication
Classifier: Programming Language :: Python :: 3
Classifier: Operating System :: OS Independent
Requires-Python: >=3.6
License-File: LICENSE
